redscope/__init__.py
redscope/__main__.py
redscope/api/__init__.py
redscope/cli/__init__.py
redscope/cli/init.py
redscope/cli/inspect.py
redscope/project/__init__.py
redscope/project/database/__init__.py
redscope/project/database/executor.py
redscope/project/database/mapper.py
redscope/project/database/models.py
redscope/project/database/queries.py
redscope/project/database/queries/columns.sql
redscope/project/database/queries/constraints.sql
redscope/project/database/queries/distkey.sql
redscope/project/database/queries/diststyle.sql
redscope/project/database/queries/functions.sql
redscope/project/database/queries/groups.sql
redscope/project/database/queries/membership.sql
redscope/project/database/queries/ownership.sql
redscope/project/database/queries/permissions.sql
redscope/project/database/queries/procedures.sql
redscope/project/database/queries/schemas.sql
redscope/project/database/queries/users.sql
redscope/project/database/queries/view.sql
redscope/project/database/queries/views.sql
redscope/project/environment/__init__.py
redscope/project/environment/environment.py
redscope/project/environment/paths.py
redscope/project/helpers/__init__.py
redscope-0.5.5.dist-info/LICENCE
redscope-0.5.5.dist-info/METADATA
redscope-0.5.5.dist-info/WHEEL
redscope-0.5.5.dist-info/entry_points.txt
redscope-0.5.5.dist-info/top_level.txt
redscope-0.5.5.dist-info/RECORD
