Metadata-Version: 2.1
Name: redscope
Version: 0.5.5
Summary: UNKNOWN
Home-page: UNKNOWN
Author: Jesse Maitland
License: UNKNOWN
Platform: UNKNOWN
Requires-Python: >=3
Requires-Dist: psycopg2-binary
Requires-Dist: python-dotenv
Requires-Dist: sqlparse
